nonebot_plugin_date_name/__init__.py
nonebot_plugin_date_name/config.py
nonebot_plugin_date_name/name.db
nonebot_plugin_date_name-3.0.dist-info/METADATA
nonebot_plugin_date_name-3.0.dist-info/WHEEL
nonebot_plugin_date_name-3.0.dist-info/top_level.txt
nonebot_plugin_date_name-3.0.dist-info/RECORD
