Metadata-Version: 2.1
Name: nonebot-plugin-date-name
Version: 3.0
Summary: 让你的群昵称显示现在时间
Home-page: https://github.com/bingqiu456/nonebot_plugin_date_name
Author: bingyue
Author-email: hello-yiqiu@qq.com
Keywords: nonebot_plugin_date_name,nonebot,nonebot_plugin
Requires-Dist: nonebot2 (>=2.0.0b2)
Requires-Dist: Pillow (>=9.1.1)
Requires-Dist: nonebot-adapter-onebot (>=2.0.0b1)
Requires-Dist: nonebot-plugin-apscheduler (>=0.1.3)
